{
    "Hawks": "atlanta-hawks-logo",
    "Celtics": "boston-celtics-logo",
    "Nets": "brooklyn-nets-logo",
    "Hornets": "charlotte-hornets-logo",
    "Bulls": "chicago-bulls-logo",
    "Cavaliers": "cleveland-cavaliers-logo",
    "Mavericks": "dallas-mavericks-logo",
    "Nuggets": "denver-nuggets-logo-2018",
    "Pistons": "detroit-pistons-logo",
    "Warriors": "golden-state-warriors-logo",
    "Rockets": "houston-rockets-logo",
    "Pacers": "indiana-pacers-logo",
    "Clippers": "la-clippers-logo",
    "Lakers": "los-angeles-lakers-logo",
    "Grizzlies": "memphis-grizzlies-logo",
    "Heat": "miami-heat-logo",
    "Bucks": "milwaukee-bucks-logo",
    "Timberwolves": "minnesota-timberwolves-logo",
    "Pelicans": "new-orleans-pelicans-logo",
    "Knicks": "new-york-knicks-logo",
    "Thunder": "oklahoma-city-thunder-logo",
    "76ers": "philadelphia-76ers-logo",
    "Suns": "phoenix-suns-logo",
    "Trail Blazers": "portland-trail-blazers-logo",
    "Kings": "sacramento-kings-logo",
    "Spurs": "san-antonio-spurs-logo",
    "Raptors": "toronto-raptors-logo",
    "Jazz": "utah-jazz-logo",
    "Wizards": "washington-wizards-logo"
}